[
  {
    "TitleRental": "Gîte Le Couderc",
    "ShortDescription": "1 gîte, 85 m2, 2 personnes, 1 chambre, 1 salle de bains",
    "Location": "COUBISOU",
    "LongDescription": "Envie de calme, de nature, de sports de plein air ? Envie de découvrir les richesses du patrimoine culturel et architectural du nord Aveyron ? Notre grange est située à proximité de la Vallée du Lot, du parc naturel régional de l'Aubrac et de nombreux villages classés parmi les plus beaux villages de France.Notre gîte est une ancienne grange entièrement rénovée avec une terrasse donnant sur une petite vallée sauvage. Randonnées possibles au départ du gîte.",
    "InformationList": "Parking privé;wifi gratuit",
    "ActivityList": "Piscine;Chemin de randonnée",
    "Description" : "Gite de 84 m2 (rez de jardin, 1er étage)",
    "EquipmentList": "Logement indépendant;Canapé",
    "BedroomTitle": "2 chambres (4 personnes)",
    "BedroomList": "Chambre 1 : 1 lit 160x190;Chambre 1 : 1 lit 160x190",
    "BathroomTitle": "1 salle de bains",
    "BathroomEquipmentList": "Logement indépendant;Canapé",
    "ToiletTitle": "2 WC",
    "KitchenList": "Réfrigérateur;Four",
    "OutsideList": "Vue sur le jardin;Vue sur la montagne;Terrasse privée",
    "AccessList": "Gare (30 km)",
    "Geolocation": "",
    "TourismList": "Station de ski du Bouyssou",
    "ServicesList": "Commerce (5km)",
    "ActivitiesList": "Lac (15km)",
    "PaymentList": "Arhes;Forfait ménage : 50 €;Location de draps : 15 € / personne",
    "FirstName": "Yann",
    "LastName": "BERDAGUÉ",
    "WebSite": "http",
    "Email": "yann.berdague@gmail.com",
    "PhoneNumber": "06 82 54 53 31",
    "Image": "https://raw.githubusercontent.com/YannB-eng/GrangeEtGites/master/Images/Gite1/image-principale.jpg",
    "ImagePath": 1,
    "NumberImages" : 10,
    "Price": 80
  },
  {
    "TitleRental": "Gîte Le Nayrac",
    "ShortDescription": "1 gîte, 85 m2, 2 personnes, 1 chambre, 1 salle de bains",
    "Location": "LE NAYRAC",
    "LongDescription": "Envie de calme, de nature, de sports de plein air ? Envie de découvrir les richesses du patrimoine culturel et architectural du nord Aveyron ? Notre grange est située à proximité de la Vallée du Lot, du parc naturel régional de l'Aubrac et de nombreux villages classés parmi les plus beaux villages de France.Notre gîte est une ancienne grange entièrement rénovée avec une terrasse donnant sur une petite vallée sauvage. Randonnées possibles au départ du gîte.",
    "InformationList": "Parking privé;wifi gratuit",
    "ActivityList": "Piscine;Chemin de randonnée",
    "Description" : "Gite de 84 m2 (rez de jardin, 1er étage)",
    "EquipmentList": "Logement indépendant;Canapé",
    "BedroomTitle": "2 chambres (4 personnes)",
    "BedroomList": "Chambre 1 : 1 lit 160x190;Chambre 1 : 1 lit 160x190",
    "BathroomTitle": "1 salle de bains",
    "BathroomEquipmentList": "Logement indépendant;Canapé",
    "ToiletTitle": "2 WC",
    "KitchenList": "Réfrigérateur;Four",
    "OutsideList": "Vue sur le jardin;Vue sur la montagne;Terrasse privée",
    "AccessList": "Gare (30 km)",
    "Geolocation": "",
    "TourismList": "Station de ski du Bouyssou",
    "ServicesList": "Commerce (5km)",
    "ActivitiesList": "Lac (15km)",
    "PaymentList": "Arhes;Forfait ménage : 50 €;Location de draps : 15 € / personne",
    "FirstName": "Yann",
    "LastName": "BERDAGUÉ",
    "WebSite": "http",
    "Email": "yann.berdague@gmail.com",
    "PhoneNumber": "06 82 54 53 31",
    "Image": "https://raw.githubusercontent.com/YannB-eng/GrangeEtGites/master/Images/Gite2/image-principale.jpg",
    "ImagePath": 2,
    "NumberImages": 8,
    "Price": 90
  }
]
